{
"gameDataType": "GameData",
"questionList": [
{ "esp": "ser, estar", "ing1": "be", "ing2": "was/were", "ing3": "been" },
{ "esp": "llegar a ser, convertirse", "ing1": "become", "ing2": "became", "ing3": "become" },
{ "esp": "empezar, comenzar", "ing1": "begin", "ing2": "began", "ing3": "begun" },
{ "esp": "traer, llevar", "ing1": "bring", "ing2": "brought", "ing3": "brought" },
{ "esp": "construir", "ing1": "build", "ing2": "built", "ing3": "built" },
{ "esp": "comprar", "ing1": "buy", "ing2": "bought", "ing3": "bought" },
{ "esp": "poder, saber, ser capaz", "ing1": "can", "ing2": "could", "ing3": "been able" },
{ "esp": "coger, atrapar", "ing1": "catch", "ing2": "caught", "ing3": "caught" },
{ "esp": "elegir, escoger", "ing1": "choose", "ing2": "chose", "ing3": "chosen" },
{ "esp": "venir", "ing1": "come", "ing2": "came", "ing3": "come" },
{ "esp": "costar", "ing1": "cost", "ing2": "cost", "ing3": "cost" },
{ "esp": "hacer", "ing1": "do", "ing2": "did", "ing3": "done" },
{ "esp": "dibujar", "ing1": "draw", "ing2": "drew", "ing3": "drawn" },
{ "esp": "beber", "ing1": "drink", "ing2": "drank", "ing3": "drunk" },
{ "esp": "conducir", "ing1": "drive", "ing2": "drove", "ing3": "driven" },
{ "esp": "comer", "ing1": "eat", "ing2": "ate", "ing3": "eaten" },
{ "esp": "caer", "ing1": "fall", "ing2": "fell", "ing3": "fallen" },
{ "esp": "alimentar", "ing1": "feed", "ing2": "fed", "ing3": "fed" },
{ "esp": "encontrar", "ing1": "find", "ing2": "found", "ing3": "found" },
{ "esp": "volar", "ing1": "fly", "ing2": "flew", "ing3": "flown" },
{ "esp": "obtener, conseguir", "ing1": "get", "ing2": "got", "ing3": "got" },
{ "esp": "dar", "ing1": "give", "ing2": "gave", "ing3": "given" },
{ "esp": "ir", "ing1": "go", "ing2": "went", "ing3": "gone" },
{ "esp": "tener", "ing1": "have", "ing2": "had", "ing3": "had" },
{ "esp": "oir, escuchar", "ing1": "hear", "ing2": "heard", "ing3": "heard" },
{ "esp": "golpear", "ing1": "hit", "ing2": "hit", "ing3": "hit" },
{ "esp": "sostener, agarrar", "ing1": "hold", "ing2": "held", "ing3": "held" },
{ "esp": "mantener, seguir (haciendo algo)", "ing1": "keep", "ing2": "kept", "ing3": "kept" },
{ "esp": "saber, conocer", "ing1": "know", "ing2": "knew", "ing3": "known" },
{ "esp": "aprender", "ing1": "learn", "ing2": "learnt", "ing3": "learnt" },
{ "esp": "abandonar", "ing1": "leave", "ing2": "left", "ing3": "left" },
{ "esp": "perder", "ing1": "lose", "ing2": "lost", "ing3": "lost" },
{ "esp": "hacer, fabricar", "ing1": "make", "ing2": "made", "ing3": "made" },
{ "esp": "significar, querer decir", "ing1": "mean", "ing2": "meant", "ing3": "meant" },
{ "esp": "conocer, encontrase (con alguien)", "ing1": "meet", "ing2": "met", "ing3": "met" },
{ "esp": "poner, colocar", "ing1": "put", "ing2": "put", "ing3": "put" },
{ "esp": "leer", "ing1": "read", "ing2": "read", "ing3": "read" },
{ "esp": "correr", "ing1": "run", "ing2": "ran", "ing3": "run" },
{ "esp": "decir", "ing1": "say", "ing2": "said", "ing3": "said" }
]
}
